web_grabber-0.5.46.dist-info/METADATA
web_grabber-0.5.46.dist-info/WHEEL
web_grabber-0.5.46.dist-info/entry_points.txt
web_grabber-0.5.46.dist-info/licenses/LICENSE.txt
web_grabber/__init__.py
web_grabber/__main__.py
web_grabber/cmd/__init__.py
web_grabber/cmd/grab/__init__.py
web_grabber/cmd/grab/grab.py
web_grabber/cmd/grab/grab_handler.py
web_grabber/lib/__init__.py
web_grabber/lib/browser_automation/__init__.py
web_grabber/lib/browser_automation/base.py
web_grabber/lib/browser_automation/camoufox_handler/__init__.py
web_grabber/lib/browser_automation/camoufox_handler/camoufox_handler.py
web_grabber/lib/browser_automation/camoufox_handler/spoofing_config.py
web_grabber/lib/browser_automation/selenium_handler/__init__.py
web_grabber/lib/browser_automation/selenium_handler/selenium_handler.py
web_grabber/lib/network/__init__.py
web_grabber/lib/network/base.py
web_grabber/lib/network/http_handler/__init__.py
web_grabber/lib/network/http_handler/http_handler.py
web_grabber/lib/network/tor_handler/__init__.py
web_grabber/lib/network/tor_handler/tor_handler.py
web_grabber/web_grabber.py
web_grabber-0.5.46.dist-info/RECORD
