Metadata-Version: 2.1
Name: web-grabber
Version: 0.5.46
Summary: A powerful CLI tool for crawling websites and downloading content including HTML, images, and videos. Features multiple browsing modes including normal requests, Selenium for JavaScript rendering, and camoufox for anti-bot protection.
Author-Email: Tadeas Fort <business@tadeasfort.com>
License: GPL-3.0
Requires-Python: >=3.10
Requires-Dist: camoufox[geoip]>=0.4.11
Requires-Dist: typer>=0.15.2
Requires-Dist: selenium>=4.29.0
Requires-Dist: requests>=2.28.1
Requires-Dist: beautifulsoup4>=4.11.1
Requires-Dist: PySocks>=1.7.1
Requires-Dist: urllib3>=1.26.12
Requires-Dist: rich>=12.6.0
Requires-Dist: httpx>=0.28.1
Requires-Dist: prompt-toolkit>=3.0.50
